psm.py
psm-0.3.0.data/scripts/psm
psm-0.3.0.dist-info/LICENSE
psm-0.3.0.dist-info/METADATA
psm-0.3.0.dist-info/WHEEL
psm-0.3.0.dist-info/top_level.txt
psm-0.3.0.dist-info/zip-safe
psm-0.3.0.dist-info/RECORD
