Metadata-Version: 2.1
Name: psm
Version: 0.3.0
Summary: Pypi Source Manager: fast switch between different Pypi Source: pypi, double, aliyun.
Home-page: http://www.jianshu.com/users/64467c788eb7
Author: brandonxiang
Author-email: 1542453460@qq.com
License: MIT
Keywords: python source package
Classifier: License :: OSI Approved :: MIT License
Classifier: Programming Language :: Python
Classifier: Programming Language :: Python :: 3.5
Classifier: Intended Audience :: Developers
Classifier: Operating System :: OS Independent
Requires-Python: >=3.5
License-File: LICENSE
Requires-Dist: docopt>=0.6.2
Requires-Dist: configparser>=7.1.0
